LICENSE
MANIFEST.in
README.rst
bootstrap-buildout.py
buildout.cfg
requirements.txt
setup.py
version.txt
bob/__init__.py
bob.learn.misc.egg-info/PKG-INFO
bob.learn.misc.egg-info/SOURCES.txt
bob.learn.misc.egg-info/dependency_links.txt
bob.learn.misc.egg-info/namespace_packages.txt
bob.learn.misc.egg-info/requires.txt
bob.learn.misc.egg-info/top_level.txt
bob/learn/__init__.py
bob/learn/misc/__init__.py
bob/learn/misc/test_em.py
bob/learn/misc/test_gaussian.py
bob/learn/misc/test_gmm.py
bob/learn/misc/test_ivector.py
bob/learn/misc/test_ivector_trainer.py
bob/learn/misc/test_jfa.py
bob/learn/misc/test_jfa_trainer.py
bob/learn/misc/test_kmeans.py
bob/learn/misc/test_kmeans_trainer.py
bob/learn/misc/test_linearscoring.py
bob/learn/misc/test_plda.py
bob/learn/misc/test_plda_trainer.py
bob/learn/misc/test_ztnorm.py
bob/learn/misc/version.cpp
bob/learn/misc/cpp/BICMachine.cpp
bob/learn/misc/cpp/BICTrainer.cpp
bob/learn/misc/cpp/EMPCATrainer.cpp
bob/learn/misc/cpp/GMMMachine.cpp
bob/learn/misc/cpp/GMMStats.cpp
bob/learn/misc/cpp/GMMTrainer.cpp
bob/learn/misc/cpp/Gaussian.cpp
bob/learn/misc/cpp/IVectorMachine.cpp
bob/learn/misc/cpp/IVectorTrainer.cpp
bob/learn/misc/cpp/JFAMachine.cpp
bob/learn/misc/cpp/JFATrainer.cpp
bob/learn/misc/cpp/KMeansMachine.cpp
bob/learn/misc/cpp/KMeansTrainer.cpp
bob/learn/misc/cpp/LinearScoring.cpp
bob/learn/misc/cpp/MAP_GMMTrainer.cpp
bob/learn/misc/cpp/ML_GMMTrainer.cpp
bob/learn/misc/cpp/PLDAMachine.cpp
bob/learn/misc/cpp/PLDATrainer.cpp
bob/learn/misc/cpp/ZTNorm.cpp
bob/learn/misc/data/data.hdf5
bob/learn/misc/data/dataNormalized.hdf5
bob/learn/misc/data/dataforMAP.hdf5
bob/learn/misc/data/faithful.torch3.hdf5
bob/learn/misc/data/faithful.torch3_f64.hdf5
bob/learn/misc/data/gmm.init_means.hdf5
bob/learn/misc/data/gmm.init_variances.hdf5
bob/learn/misc/data/gmm.init_weights.hdf5
bob/learn/misc/data/gmm_MAP.hdf5
bob/learn/misc/data/gmm_ML.hdf5
bob/learn/misc/data/gmm_ML_32bit_debug.hdf5
bob/learn/misc/data/gmm_ML_32bit_release.hdf5
bob/learn/misc/data/means.hdf5
bob/learn/misc/data/meansAfterKMeans.hdf5
bob/learn/misc/data/meansAfterMAP.hdf5
bob/learn/misc/data/meansAfterML.hdf5
bob/learn/misc/data/new_adapted_mean.hdf5
bob/learn/misc/data/samplesFrom2G_f64.hdf5
