Metadata-Version: 1.1
Name: bob.learn.misc
Version: 2.0.1
Summary: Bindings for miscelaneous machines and trainers of Bob
Home-page: http://github.com/bioidiap/bob.learn.misc
Author: Andre Anjos
Author-email: andre.anjos@idiap.ch
License: BSD
Platform: UNKNOWN
Classifier: Framework :: Bob
Classifier: Development Status :: 3 - Alpha
Classifier: Intended Audience :: Developers
Classifier: License :: OSI Approved :: BSD License
Classifier: Natural Language :: English
Classifier: Programming Language :: Python
Classifier: Programming Language :: Python :: 3
Classifier: Topic :: Software Development :: Libraries :: Python Modules
